<?xml version="1.0" encoding="UTF-8"?>
<VYSLEDKY_OKRSKY xmlns="http://www.volby.cz/kv/" xmlns:xsi="http://www.w3.org/2001/XMLSchema-instance"
                  xsi:schemaLocation="http://www.volby.cz/kv/ kv_vysledky_okrsky.xsd"
                  DATUM_CAS_GENEROVANI="2022-09-25T02:55:00">
<DAVKA DATUMVOLEB="20220923" PORADI_DAVKY="145" OKRSKY_DAVKA="2" OKRSKY_CELKEM="16854" OKRSKY_ZPRAC="16839"/>
<OKRSEK CIS_OBEC="547034" CIS_OKRSEK="11018" KODZASTUP="554782" CIS_OBVODU="1" OZNAC_TYPU="OBEC" PORADI_ZPRAC="16881" DATUM_CAS_ZPRAC="2022-09-25T02:52:16" OPAKOVANE="0">
<UCAST_OKRSEK ZAPSANI_VOLICI="810" VYDANE_OBALKY="296" ODEVZDANE_OBALKY="295" PLATNE_HLASY="16816"/>
<HLASY_OKRSEK POR_STR_HLAS_LIST="1" HLASY="21"/>
<HLASY_OKRSEK POR_STR_HLAS_LIST="2" HLASY="105"/>
<HLASY_OKRSEK POR_STR_HLAS_LIST="3" HLASY="132"/>
<HLASY_OKRSEK POR_STR_HLAS_LIST="4" HLASY="1133"/>
<HLASY_OKRSEK POR_STR_HLAS_LIST="5" HLASY="457"/>
<HLASY_OKRSEK POR_STR_HLAS_LIST="6" HLASY="825"/>
<HLASY_OKRSEK POR_STR_HLAS_LIST="7" HLASY="2"/>
<HLASY_OKRSEK POR_STR_HLAS_LIST="8" HLASY="1656"/>
<HLASY_OKRSEK POR_STR_HLAS_LIST="9" HLASY="200"/>
<HLASY_OKRSEK POR_STR_HLAS_LIST="10" HLASY="341"/>
<HLASY_OKRSEK POR_STR_HLAS_LIST="11" HLASY="0"/>
<HLASY_OKRSEK POR_STR_HLAS_LIST="12" HLASY="1"/>
<HLASY_OKRSEK POR_STR_HLAS_LIST="13" HLASY="263"/>
<HLASY_OKRSEK POR_STR_HLAS_LIST="14" HLASY="3681"/>
<HLASY_OKRSEK POR_STR_HLAS_LIST="15" HLASY="281"/>
<HLASY_OKRSEK POR_STR_HLAS_LIST="16" HLASY="859"/>
<HLASY_OKRSEK POR_STR_HLAS_LIST="17" HLASY="1"/>
<HLASY_OKRSEK POR_STR_HLAS_LIST="18" HLASY="0"/>
<HLASY_OKRSEK POR_STR_HLAS_LIST="19" HLASY="0"/>
<HLASY_OKRSEK POR_STR_HLAS_LIST="20" HLASY="2"/>
<HLASY_OKRSEK POR_STR_HLAS_LIST="21" HLASY="6843"/>
<HLASY_OKRSEK POR_STR_HLAS_LIST="22" HLASY="13"/>
</OKRSEK>
<OKRSEK CIS_OBEC="547034" CIS_OKRSEK="11018" KODZASTUP="547034" CIS_OBVODU="1" OZNAC_TYPU="MCMO" PORADI_ZPRAC="16882" DATUM_CAS_ZPRAC="2022-09-25T02:52:21" OPAKOVANE="0">
<UCAST_OKRSEK ZAPSANI_VOLICI="810" VYDANE_OBALKY="296" ODEVZDANE_OBALKY="295" PLATNE_HLASY="9331"/>
<HLASY_OKRSEK POR_STR_HLAS_LIST="1" HLASY="699"/>
<HLASY_OKRSEK POR_STR_HLAS_LIST="2" HLASY="3269"/>
<HLASY_OKRSEK POR_STR_HLAS_LIST="3" HLASY="387"/>
<HLASY_OKRSEK POR_STR_HLAS_LIST="4" HLASY="112"/>
<HLASY_OKRSEK POR_STR_HLAS_LIST="5" HLASY="2166"/>
<HLASY_OKRSEK POR_STR_HLAS_LIST="6" HLASY="710"/>
<HLASY_OKRSEK POR_STR_HLAS_LIST="7" HLASY="620"/>
<HLASY_OKRSEK POR_STR_HLAS_LIST="8" HLASY="1229"/>
<HLASY_OKRSEK POR_STR_HLAS_LIST="9" HLASY="139"/>
</OKRSEK>
</VYSLEDKY_OKRSKY>
