<?xml version="1.0" encoding="UTF-8"?>
<VYSLEDKY_OKRSKY xmlns="http://www.volby.cz/kv/" xmlns:xsi="http://www.w3.org/2001/XMLSchema-instance"
                  xsi:schemaLocation="http://www.volby.cz/kv/ kv_vysledky_okrsky.xsd"
                  DATUM_CAS_GENEROVANI="2022-09-25T03:15:01">
<DAVKA DATUMVOLEB="20220923" PORADI_DAVKY="148" OKRSKY_DAVKA="2" OKRSKY_CELKEM="16854" OKRSKY_ZPRAC="16846"/>
<OKRSEK CIS_OBEC="538205" CIS_OKRSEK="31001" KODZASTUP="538205" CIS_OBVODU="1" OZNAC_TYPU="MCMO" PORADI_ZPRAC="16889" DATUM_CAS_ZPRAC="2022-09-25T03:13:56" OPAKOVANE="0">
<UCAST_OKRSEK ZAPSANI_VOLICI="1772" VYDANE_OBALKY="915" ODEVZDANE_OBALKY="908" PLATNE_HLASY="11532"/>
<HLASY_OKRSEK POR_STR_HLAS_LIST="1" HLASY="6027"/>
<HLASY_OKRSEK POR_STR_HLAS_LIST="2" HLASY="2245"/>
<HLASY_OKRSEK POR_STR_HLAS_LIST="3" HLASY="3260"/>
</OKRSEK>
<OKRSEK CIS_OBEC="538205" CIS_OKRSEK="31001" KODZASTUP="554782" CIS_OBVODU="1" OZNAC_TYPU="OBEC" PORADI_ZPRAC="16890" DATUM_CAS_ZPRAC="2022-09-25T03:14:34" OPAKOVANE="0">
<UCAST_OKRSEK ZAPSANI_VOLICI="1772" VYDANE_OBALKY="915" ODEVZDANE_OBALKY="908" PLATNE_HLASY="48531"/>
<HLASY_OKRSEK POR_STR_HLAS_LIST="1" HLASY="412"/>
<HLASY_OKRSEK POR_STR_HLAS_LIST="2" HLASY="487"/>
<HLASY_OKRSEK POR_STR_HLAS_LIST="3" HLASY="179"/>
<HLASY_OKRSEK POR_STR_HLAS_LIST="4" HLASY="3928"/>
<HLASY_OKRSEK POR_STR_HLAS_LIST="5" HLASY="56"/>
<HLASY_OKRSEK POR_STR_HLAS_LIST="6" HLASY="3890"/>
<HLASY_OKRSEK POR_STR_HLAS_LIST="7" HLASY="7"/>
<HLASY_OKRSEK POR_STR_HLAS_LIST="8" HLASY="5808"/>
<HLASY_OKRSEK POR_STR_HLAS_LIST="9" HLASY="1103"/>
<HLASY_OKRSEK POR_STR_HLAS_LIST="10" HLASY="49"/>
<HLASY_OKRSEK POR_STR_HLAS_LIST="11" HLASY="5"/>
<HLASY_OKRSEK POR_STR_HLAS_LIST="12" HLASY="4"/>
<HLASY_OKRSEK POR_STR_HLAS_LIST="13" HLASY="916"/>
<HLASY_OKRSEK POR_STR_HLAS_LIST="14" HLASY="15840"/>
<HLASY_OKRSEK POR_STR_HLAS_LIST="15" HLASY="1396"/>
<HLASY_OKRSEK POR_STR_HLAS_LIST="16" HLASY="2100"/>
<HLASY_OKRSEK POR_STR_HLAS_LIST="17" HLASY="40"/>
<HLASY_OKRSEK POR_STR_HLAS_LIST="18" HLASY="5"/>
<HLASY_OKRSEK POR_STR_HLAS_LIST="19" HLASY="0"/>
<HLASY_OKRSEK POR_STR_HLAS_LIST="20" HLASY="75"/>
<HLASY_OKRSEK POR_STR_HLAS_LIST="21" HLASY="12210"/>
<HLASY_OKRSEK POR_STR_HLAS_LIST="22" HLASY="21"/>
</OKRSEK>
</VYSLEDKY_OKRSKY>
